dawg_baas/__init__.py
dawg_baas/client.py
dawg_baas/exceptions.py
dawg_baas/py.typed
dawg_baas/version.py
dawg_baas-0.1.0.dist-info/METADATA
dawg_baas-0.1.0.dist-info/WHEEL
dawg_baas-0.1.0.dist-info/licenses/LICENSE
dawg_baas-0.1.0.dist-info/RECORD
