Metadata-Version: 2.4
Name: dawg-baas
Version: 0.1.0
Summary: Python SDK for BaaS (Browser as a Service) - managed headless browsers via CDP
Project-URL: Homepage, https://github.com/nicejji/dawg-baas
Project-URL: Repository, https://github.com/nicejji/dawg-baas
Project-URL: Issues, https://github.com/nicejji/dawg-baas/issues
Author: DAWG Team
License-Expression: MIT
License-File: LICENSE
Keywords: automation,baas,browser,cdp,headless,playwright,scraping
Classifier: Development Status :: 4 - Beta
Classifier: Intended Audience :: Developers
Classifier: License :: OSI Approved :: MIT License
Classifier: Programming Language :: Python :: 3
Classifier: Programming Language :: Python :: 3.9
Classifier: Programming Language :: Python :: 3.10
Classifier: Programming Language :: Python :: 3.11
Classifier: Programming Language :: Python :: 3.12
Classifier: Topic :: Internet :: WWW/HTTP :: Browsers
Classifier: Topic :: Software Development :: Libraries :: Python Modules
Requires-Python: >=3.9
Requires-Dist: httpx>=0.25.0
Requires-Dist: requests>=2.28.0
Provides-Extra: dev
Requires-Dist: mypy>=1.0.0; extra == 'dev'
Requires-Dist: pytest-asyncio>=0.21.0; extra == 'dev'
Requires-Dist: pytest-cov>=4.0.0; extra == 'dev'
Requires-Dist: pytest>=7.0.0; extra == 'dev'
Requires-Dist: ruff>=0.1.0; extra == 'dev'
